kozip/KoZIP.py
kozip/__init__.py
kozip/new_zip.json
kozip/old_zip.json
kozip-1.1.4.dist-info/LICENSE
kozip-1.1.4.dist-info/METADATA
kozip-1.1.4.dist-info/WHEEL
kozip-1.1.4.dist-info/top_level.txt
kozip-1.1.4.dist-info/RECORD
