Metadata-Version: 2.1
Name: kozip
Version: 1.1.4
Summary: Convert Korean ZIP code to address
Home-page: https://github.com/HeekangPark/KoZIP
Author: Heekang Park
Author-email: park.heekang33@gmail.com
License: MIT
Platform: UNKNOWN
Classifier: Programming Language :: Python :: 3
Classifier: License :: OSI Approved :: MIT License
Classifier: Operating System :: OS Independent
Requires-Python: >=3
License-File: LICENSE
